edgarquery/__about__.py
edgarquery/__init__.py
edgarquery/aa2html.py
edgarquery/cikperson.py
edgarquery/companyconceptparse.py
edgarquery/companyconcepttocsv.py
edgarquery/companyfactsparse.py
edgarquery/companyfactsshow.py
edgarquery/companyfactstocsv.py
edgarquery/companyfactsziptocsv.py
edgarquery/companyfactzip2db.py
edgarquery/ebquery.py
edgarquery/edgarcikperson.py
edgarquery/edgarcompanyconcepttocsv.py
edgarquery/edgarcompanyfactsshow.py
edgarquery/edgarcompanyfactstocsv.py
edgarquery/edgarcompanyfactsziptocsv.py
edgarquery/edgarlatest10K.py
edgarquery/edgarlatestsubmission.py
edgarquery/edgarlatestsubmissions.py
edgarquery/edgarquery.py
edgarquery/edgarsubmissions.py
edgarquery/edgarsubmissionspivot.py
edgarquery/edgarsubmissionsziptocsv.py
edgarquery/edgartickerstocsv.py
edgarquery/edgarxbrlframestocsv.py
edgarquery/insidertrading.py
edgarquery/latest10K.py
edgarquery/latestsubmissions.py
edgarquery/sedfile
edgarquery/submissions.py
edgarquery/submissionsziptocsv.py
edgarquery/tickerd.py
edgarquery/tickerstocsv.py
edgarquery/xbrlframesparse.py
edgarquery/xbrlframestocsv.py
edgarquery-0.0.86.dist-info/METADATA
edgarquery-0.0.86.dist-info/WHEEL
edgarquery-0.0.86.dist-info/entry_points.txt
edgarquery-0.0.86.dist-info/licenses/LICENSE.txt
edgarquery-0.0.86.dist-info/RECORD
