Metadata-Version: 2.4
Name: edgarquery
Version: 0.0.86
Summary: Downloads various SEC EDGAR files by CIK or ticker.  companyfactsshow displays company facts in your browser
Project-URL: Documentation, https://github.com/dfwcnj/edgarquery#readme
Project-URL: Issues, https://github.com/dfwcnj/edgarquery/issues
Project-URL: Source, https://github.com/dfwcnj/edgarquery
Author-email: Don Caldwell <dfwcnj@gmail.com>
License-Expression: MIT
License-File: LICENSE.txt
Classifier: Development Status :: 4 - Beta
Classifier: Programming Language :: Python
Classifier: Programming Language :: Python :: 3.8
Classifier: Programming Language :: Python :: 3.9
Classifier: Programming Language :: Python :: 3.10
Classifier: Programming Language :: Python :: 3.11
Classifier: Programming Language :: Python :: 3.12
Classifier: Programming Language :: Python :: Implementation :: CPython
Classifier: Programming Language :: Python :: Implementation :: PyPy
Requires-Python: >=3.8
